landbosse/__init__.py
landbosse/excelio/CsvGenerator.py
landbosse/excelio/GridSearchTree.py
landbosse/excelio/WeatherWindowCSVReader.py
landbosse/excelio/XlsxDataframeCache.py
landbosse/excelio/XlsxFileOperations.py
landbosse/excelio/XlsxGenerator.py
landbosse/excelio/XlsxManagerRunner.py
landbosse/excelio/XlsxOperationException.py
landbosse/excelio/XlsxParallelManagerRunner.py
landbosse/excelio/XlsxReader.py
landbosse/excelio/XlsxSerialManagerRunner.py
landbosse/excelio/XlsxValidator.py
landbosse/excelio/__init__.py
landbosse/landbosse_api/__init__.py
landbosse/landbosse_api/project_list.xlsx
landbosse/landbosse_api/run.py
landbosse/landbosse_api/turbine_scaling.py
landbosse/landbosse_api/project_data/az_rolling.srw
landbosse/landbosse_api/project_data/ge15_public.xlsx
landbosse/model/CollectionCost.py
landbosse/model/CostModule.py
landbosse/model/DefaultMasterInputDict.py
landbosse/model/DevelopmentCost.py
landbosse/model/ErectionCost.py
landbosse/model/FoundationCost.py
landbosse/model/GridConnectionCost.py
landbosse/model/ManagementCost.py
landbosse/model/Manager.py
landbosse/model/SitePreparationCost.py
landbosse/model/SubstationCost.py
landbosse/model/WeatherDelay.py
landbosse/model/__init__.py
landbosse/tests/__init__.py
landbosse/tests/model/__init__.py
landbosse/tests/model/test_CollectionCost.py
landbosse/tests/model/test_DevelopmentCost.py
landbosse/tests/model/test_ErectionCost.py
landbosse/tests/model/test_FoundationCost.py
landbosse/tests/model/test_GridConnectionCost.py
landbosse/tests/model/test_ManagementCost.py
landbosse/tests/model/test_SitePreparationCost.py
landbosse/tests/model/test_SubstationCost.py
landbosse/tests/model/test_WeatherDelay.py
landbosse/tests/model/test_filename_functions.py
landbosse-2.3.0.3.dist-info/LICENSE.txt
landbosse-2.3.0.3.dist-info/METADATA
landbosse-2.3.0.3.dist-info/WHEEL
landbosse-2.3.0.3.dist-info/top_level.txt
landbosse-2.3.0.3.dist-info/RECORD
