Metadata-Version: 2.1
Name: landbosse
Version: 2.3.0.3
Summary: LandBOSSE
Home-page: https://github.com/WISDEM/LandBOSSE
Author: NREL
Author-email: Parangat.Bhaskar@nrel.gov
License: UNKNOWN
Platform: UNKNOWN
Requires-Python: >=3.6
Requires-Dist: pandas (==1.0.3)
Requires-Dist: numpy (==1.17.2)
Requires-Dist: sympy (==1.4)
Requires-Dist: scipy (==1.3.1)
Requires-Dist: xlsxwriter (==1.2.1)
Requires-Dist: xlrd (==1.2.0)
Requires-Dist: pytest (==5.3.5)
